changelog_cli/__init__.py
changelog_cli/cli/__init__.py
changelog_cli/cli/main.py
changelog_cli/cli/commands/__init__.py
changelog_cli/cli/commands/generate.py
changelog_cli/cli/commands/web.py
changelog_cli/core/__init__.py
changelog_cli/core/changelog.py
changelog_cli/core/git.py
changelog_cli/services/__init__.py
changelog_cli/services/ai_service.py
changelog_cli/services/markdown_service.py
changelog_cli/web/__init__.py
changelog_cli/web/app.py
changelog_cli/web/config.py
changelog_cli/web/routes.py
changelog_cli/web/templates/index.html
brose_changelog_cli-0.1.1.dist-info/METADATA
brose_changelog_cli-0.1.1.dist-info/WHEEL
brose_changelog_cli-0.1.1.dist-info/entry_points.txt
brose_changelog_cli-0.1.1.dist-info/top_level.txt
brose_changelog_cli-0.1.1.dist-info/RECORD
