Metadata-Version: 2.2
Name: brose-changelog-cli
Version: 0.1.1
Summary: AI-powered changelog generator from git commits
Author-email: bruno <contact@brunorodriguez.dev>
Classifier: Development Status :: 3 - Alpha
Classifier: Intended Audience :: Developers
Classifier: Topic :: Software Development :: Documentation
Classifier: License :: OSI Approved :: MIT License
Classifier: Programming Language :: Python :: 3.12
Requires-Python: >=3.12
Requires-Dist: fastapi>=0.115.8
Requires-Dist: jinja2>=3.1.5
Requires-Dist: markdown>=3.7
Requires-Dist: openai>=1.61.1
Requires-Dist: pydantic>=2.10.6
Requires-Dist: python-dotenv>=1.0.1
Requires-Dist: python-multipart>=0.0.20
Requires-Dist: typer>=0.15.1
Requires-Dist: uvicorn>=0.34.0
Provides-Extra: web
Requires-Dist: fastapi>=0.115.8; extra == "web"
Requires-Dist: uvicorn>=0.34.0; extra == "web"
Requires-Dist: jinja2>=3.1.5; extra == "web"
Requires-Dist: markdown>=3.7; extra == "web"
